{
 "background": "#fafafa",
 "bar_background": "#fafafa",
 "default_text": "#333333",
 "error_text": "#ce5149",
 "gutter_background": "#f3f3f3",
 "gutter_border": "#dddddd",
 "interstitial": "#fafafa",
 "library_background": "#fafafa",
 "line_number": "#a5a5a5",
 "name": "Dawn",
 "scopes": {
  "bold": {
   "font-style": "bold"
  },
  "bold-italic": {
   "font-style": "bold-italic"
  },
  "builtinfunction": {
   "color": "#ca6335"
  },
  "checkbox": {
   "checkbox": true
  },
  "checkbox-done": {
   "checkbox": true,
   "done": true
  },
  "class": {
   "color": "#ca6335"
  },
  "classdef": {
   "color": "#ca6335",
   "font-style": "bold"
  },
  "code": {
   "background-color": "#80808020",
   "corner-radius": 2.0
  },
  "codeblock-start": {
   "color": "#80808080"
  },
  "comment": {
   "color": "#6d6672",
   "font-style": "italic"
  },
  "decorator": {
   "color": "#ca6335"
  },
  "default": {
   "color": "#000000"
  },
  "docstring": {
   "color": "#117133",
   "font-style": "italic"
  },
  "formatting": {
   "color": "#80808080"
  },
  "function": {
   "color": "#ca6335"
  },
  "functiondef": {
   "color": "#ca6335",
   "font-style": "bold"
  },
  "heading-1": {
   "font-style": "bold"
  },
  "heading-2": {
   "font-style": "bold"
  },
  "heading-3": {
   "font-style": "bold"
  },
  "italic": {
   "font-style": "italic"
  },
  "keyword": {
   "color": "#b53570"
  },
  "link": {
   "text-decoration": "underline"
  },
  "module": {
   "color": "#8b5c4a"
  },
  "number": {
   "color": "#932f32"
  },
  "project": {
   "font-style": "bold"
  },
  "string": {
   "color": "#117133"
  },
  "tag": {
   "text-decoration": "none"
  },
  "task-done": {
   "color": "#66666680",
   "text-decoration": "strikeout"
  }
 },
 "separator_line": "#b3b3b3",
 "tab_background": "#f0f0f0",
 "tab_title": "#000000",
 "text_selection_tint": "#3061a6",
 "thumbnail_border": "#d1d1d1",
 "tint": "#3061a6"
}